vocal/__init__.py
vocal/cli.py
vocal-0.0.5.dist-info/METADATA
vocal-0.0.5.dist-info/WHEEL
vocal-0.0.5.dist-info/entry_points.txt
vocal-0.0.5.dist-info/licenses/LICENSE
vocal-0.0.5.dist-info/RECORD
