Metadata-Version: 2.3
Name: vocal
Version: 0.0.5
Summary: A vocal source separation
Project-URL: Homepage, https://github.com/seanghay/vocal
Project-URL: Repository, https://github.com/seanghay/vocal
Author-email: Seanghay Yath <seanghay.dev@gmail.com>
License: MIT License
License-File: LICENSE
Classifier: Development Status :: 4 - Beta
Classifier: Intended Audience :: Developers
Classifier: License :: OSI Approved :: MIT License
Classifier: Programming Language :: Python :: 3.8
Classifier: Topic :: Scientific/Engineering :: Artificial Intelligence
Requires-Dist: click
Requires-Dist: huggingface-hub
Requires-Dist: librosa
Requires-Dist: numpy
Requires-Dist: soundfile
Requires-Dist: torch
Requires-Dist: tqdm
